api/__init__.py
api/config.py
api/dependencies.py
api/main.py
api/models.py
sdk/__init__.py
services/__init__.py
services/bounding_boxes.py
services/file_storage.py
services/gemini_service.py
vlms/__init__.py
vlas-0.0.0.dist-info/METADATA
vlas-0.0.0.dist-info/WHEEL
vlas-0.0.0.dist-info/top_level.txt
vlas-0.0.0.dist-info/RECORD
