Metadata-Version: 2.4
Name: vlas
Version: 0.0.0
Summary: VLMS - Video Intelligence SDK
Author-email: Rishabh <rishabh@observee.com>
